{"skeleton":{"hash":"xNVXTph9IcpfWS2d7TNpUh6zunY","spine":"3.8.99","x":-168.5,"y":-168.5,"width":337,"height":337},"bones":[{"name":"root"},{"name":"bone","parent":"root"},{"name":"bone2","parent":"bone","length":133.79,"rotation":90},{"name":"bone3","parent":"bone","length":133.79,"rotation":-0.1}],"slots":[{"name":"1","bone":"bone2","attachment":"1"},{"name":"2","bone":"bone3","attachment":"2","blend":"additive"}],"skins":[{"name":"default","attachments":{"1":{"1":{"rotation":0.17,"width":336,"height":336}},"2":{"2":{"rotation":0.1,"width":282,"height":278}}}}],"animations":{"animation":{"slots":{"2":{"color":[{"color":"ffffffff"},{"time":2,"color":"ffffff00"},{"time":4,"color":"ffffffff"}]}},"bones":{"bone3":{"rotate":[{},{"time":0.5,"angle":-89.9},{"time":1,"angle":179.99},{"time":1.5,"angle":90.1},{"time":2},{"time":2.5,"angle":-89.9},{"time":3,"angle":179.99},{"time":3.5,"angle":90.1},{"time":4}],"scale":[{},{"time":2,"x":0.3,"y":0.3},{"time":4}]},"bone2":{"rotate":[{},{"time":0.5,"angle":-90},{"time":1,"angle":180},{"time":1.5,"angle":90},{"time":2},{"time":2.5,"angle":-90},{"time":3,"angle":180},{"time":3.5,"angle":90},{"time":4}]}}}}}